onegov.form-0.46.6-py3.6-nspkg.pth
onegov/form/.gitignore
onegov/form/__init__.py
onegov/form/collection.py
onegov/form/core.py
onegov/form/display.py
onegov/form/errors.py
onegov/form/extensions.py
onegov/form/fields.py
onegov/form/filters.py
onegov/form/integration.py
onegov/form/upgrade.py
onegov/form/utils.py
onegov/form/validators.py
onegov/form/widgets.py
onegov/form/assets/css/chosen.css
onegov/form/assets/css/iconwidget.css
onegov/form/assets/css/preview-widget.css
onegov/form/assets/css/images/chosen-sprite.png
onegov/form/assets/css/images/chosen-sprite@2x.png
onegov/form/assets/js/chosen-init.js
onegov/form/assets/js/chosen.jquery.js
onegov/form/assets/js/format.jsx
onegov/form/assets/js/iconwidget.js
onegov/form/assets/js/preview-widget.js
onegov/form/assets/js/select.jsx
onegov/form/assets/js/snippets.jsx
onegov/form/assets/js/togglebutton.jsx
onegov/form/assets/js/utils.js
onegov/form/assets/js/watcher.jsx
onegov/form/locale/de_ch/LC_MESSAGES/onegov.form.po
onegov/form/locale/fr_CH/LC_MESSAGES/onegov.form.po
onegov/form/locale/it_CH/LC_MESSAGES/onegov.form.po
onegov/form/locale/rm_CH/LC_MESSAGES/onegov.form.po
onegov/form/models/__init__.py
onegov/form/models/definition.py
onegov/form/models/registration_window.py
onegov/form/models/submission.py
onegov/form/parser/__init__.py
onegov/form/parser/core.py
onegov/form/parser/errors.py
onegov/form/parser/form.py
onegov/form/parser/grammar.py
onegov/form/parser/snippets.py
onegov/form/tests/conftest.py
onegov/form/tests/test_browser.py
onegov/form/tests/test_collection.py
onegov/form/tests/test_core.py
onegov/form/tests/test_display.py
onegov/form/tests/test_fields.py
onegov/form/tests/test_grammar.py
onegov/form/tests/test_model.py
onegov/form/tests/test_parser.py
onegov/form/tests/test_utils.py
onegov/form/tests/test_validators.py
onegov.form-0.46.6.dist-info/METADATA
onegov.form-0.46.6.dist-info/WHEEL
onegov.form-0.46.6.dist-info/entry_points.txt
onegov.form-0.46.6.dist-info/namespace_packages.txt
onegov.form-0.46.6.dist-info/top_level.txt
onegov.form-0.46.6.dist-info/RECORD
