Metadata-Version: 2.1
Name: onegov.form
Version: 0.46.6
Summary: Common OneGov form library based on WTForms.
Home-page: http://github.com/onegov/onegov.form
Author: Seantis GmbH
Author-email: info@seantis.ch
License: GPLv2
Platform: any
Classifier: Intended Audience :: Developers
Classifier: Programming Language :: Python :: 3 :: Only
Classifier: Programming Language :: Python :: 3.6
Classifier: Programming Language :: Python :: 3.7
Classifier: Topic :: Software Development :: Libraries :: Python Modules
Classifier: License :: OSI Approved :: GNU General Public License v2 (GPLv2)
Requires-Python: >=3.6
Requires-Dist: cached-property
Requires-Dist: chameleon
Requires-Dist: colour (>=0.0.4)
Requires-Dist: humanize
Requires-Dist: jsonpickle
Requires-Dist: mistune
Requires-Dist: more.webassets
Requires-Dist: onegov.core (>=0.70.5)
Requires-Dist: onegov.file
Requires-Dist: onegov.pay
Requires-Dist: phonenumbers
Requires-Dist: pyparsing (>=2.3.1)
Requires-Dist: pyyaml
Requires-Dist: python-dateutil
Requires-Dist: python-stdnum
Requires-Dist: sedate
Requires-Dist: sqlalchemy-utils
Requires-Dist: wtforms (>=2.2)
Requires-Dist: wtforms-components
Requires-Dist: unidecode
Provides-Extra: test
Requires-Dist: coverage ; extra == 'test'
Requires-Dist: onegov-testing ; extra == 'test'
Requires-Dist: pytest ; extra == 'test'
Requires-Dist: pytest-localserver ; extra == 'test'
Requires-Dist: webob ; extra == 'test'
Requires-Dist: werkzeug ; extra == 'test'
